<?xml version="1.0" encoding="UTF-8"?>
<!--oriflamms data file-->
<OriData>
    <validation>
        <v id="w_mss-dates_7624" ok="2" left="0" right="0" imgsig=""/>
        <v id="w_mss-dates_7592" ok="2" left="0" right="0" imgsig=""/>
        <v id="w_mss-dates_7699" ok="2" left="0" right="0" imgsig=""/>
        <v id="w_mss-dates_7625" ok="2" left="0" right="0" imgsig=""/>
        <v id="w_mss-dates_7593" ok="2" left="0" right="0" imgsig=""/>
        <v id="w_mss-dates_7698" ok="2" left="0" right="0" imgsig=""/>
        <v id="w_mss-dates_7622" ok="2" left="0" right="0" imgsig=""/>
        <v id="w_mss-dates_7594" ok="2" left="0" right="0" imgsig=""/>
        <v id="w_mss-dates_7595" ok="2" left="0" right="0" imgsig=""/>
        <v id="w_mss-dates_7623" ok="2" left="0" right="0" imgsig=""/>
        <v id="w_mss-dates_7596" ok="2" left="0" right="0" imgsig=""/>
        <v id="w_mss-dates_7620" ok="2" left="0" right="0" imgsig=""/>
        <v id="w_mss-dates_7597" ok="2" left="0" right="0" imgsig=""/>
        <v id="w_mss-dates_7621" ok="2" left="0" right="0" imgsig=""/>
        <v id="w_mss-dates_7600" ok="2" left="0" right="0" imgsig=""/>
        <v id="w_mss-dates_7693" ok="2" left="0" right="0" imgsig=""/>
        <v id="w_mss-dates_7598" ok="2" left="0" right="0" imgsig=""/>
        <v id="w_mss-dates_7631" ok="2" left="0" right="0" imgsig=""/>
        <v id="w_mss-dates_7692" ok="2" left="0" right="0" imgsig=""/>
        <v id="w_mss-dates_7599" ok="2" left="0" right="0" imgsig=""/>
        <v id="w_mss-dates_7630" ok="2" left="0" right="0" imgsig=""/>
        <v id="w_mss-dates_7601" ok="2" left="0" right="0" imgsig=""/>
        <v id="w_mss-dates_7602" ok="2" left="0" right="0" imgsig=""/>
        <v id="w_mss-dates_7603" ok="2" left="0" right="0" imgsig=""/>
        <v id="w_mss-dates_7604" ok="2" left="0" right="0" imgsig=""/>
        <v id="w_mss-dates_7605" ok="2" left="0" right="0" imgsig=""/>
        <v id="w_mss-dates_7606" ok="2" left="0" right="0" imgsig=""/>
        <v id="w_mss-dates_7607" ok="2" left="0" right="0" imgsig=""/>
        <v id="w_mss-dates_7608" ok="2" left="0" right="0" imgsig=""/>
        <v id="w_mss-dates_7609" ok="2" left="0" right="0" imgsig=""/>
        <v id="w_mss-dates_7656" ok="2" left="0" right="0" imgsig=""/>
        <v id="w_mss-dates_7610" ok="2" left="0" right="0" imgsig=""/>
        <v id="w_mss-dates_7611" ok="2" left="0" right="0" imgsig=""/>
        <v id="w_mss-dates_7612" ok="2" left="0" right="0" imgsig=""/>
        <v id="w_mss-dates_7613" ok="2" left="0" right="0" imgsig=""/>
        <v id="w_mss-dates_7614" ok="2" left="0" right="0" imgsig=""/>
        <v id="w_mss-dates_7615" ok="2" left="0" right="0" imgsig=""/>
        <v id="w_mss-dates_7616" ok="2" left="0" right="0" imgsig=""/>
        <v id="w_mss-dates_7617" ok="2" left="0" right="0" imgsig=""/>
        <v id="w_mss-dates_7618" ok="2" left="0" right="0" imgsig=""/>
        <v id="w_mss-dates_7619" ok="2" left="0" right="0" imgsig=""/>
        <v id="w_mss-dates_7626" ok="2" left="0" right="0" imgsig=""/>
        <v id="w_mss-dates_7639" ok="2" left="0" right="0" imgsig=""/>
        <v id="w_mss-dates_7627" ok="2" left="0" right="0" imgsig=""/>
        <v id="w_mss-dates_7638" ok="2" left="0" right="0" imgsig=""/>
        <v id="w_mss-dates_7628" ok="2" left="0" right="0" imgsig=""/>
        <v id="w_mss-dates_7637" ok="2" left="0" right="0" imgsig=""/>
        <v id="w_mss-dates_7629" ok="2" left="0" right="0" imgsig=""/>
        <v id="w_mss-dates_7636" ok="2" left="0" right="0" imgsig=""/>
        <v id="w_mss-dates_7632" ok="2" left="0" right="0" imgsig=""/>
        <v id="w_mss-dates_7633" ok="2" left="0" right="0" imgsig=""/>
        <v id="w_mss-dates_7634" ok="2" left="0" right="0" imgsig=""/>
        <v id="w_mss-dates_7635" ok="2" left="0" right="0" imgsig=""/>
        <v id="w_mss-dates_7640" ok="2" left="0" right="0" imgsig=""/>
        <v id="w_mss-dates_7641" ok="2" left="0" right="0" imgsig=""/>
        <v id="w_mss-dates_7642" ok="2" left="0" right="0" imgsig=""/>
        <v id="w_mss-dates_7643" ok="2" left="0" right="0" imgsig=""/>
        <v id="w_mss-dates_7644" ok="2" left="0" right="0" imgsig=""/>
        <v id="w_mss-dates_7645" ok="2" left="0" right="0" imgsig=""/>
        <v id="w_mss-dates_7646" ok="2" left="0" right="0" imgsig=""/>
        <v id="w_mss-dates_7647" ok="2" left="0" right="0" imgsig=""/>
        <v id="w_mss-dates_7648" ok="2" left="0" right="0" imgsig=""/>
        <v id="w_mss-dates_7649" ok="2" left="0" right="0" imgsig=""/>
        <v id="w_mss-dates_7650" ok="2" left="0" right="0" imgsig=""/>
        <v id="w_mss-dates_7651" ok="2" left="0" right="0" imgsig=""/>
        <v id="w_mss-dates_7652" ok="2" left="0" right="0" imgsig=""/>
        <v id="w_mss-dates_7653" ok="2" left="0" right="0" imgsig=""/>
        <v id="w_mss-dates_7654" ok="2" left="0" right="0" imgsig=""/>
        <v id="w_mss-dates_7655" ok="2" left="0" right="0" imgsig=""/>
        <v id="w_mss-dates_7657" ok="2" left="0" right="0" imgsig=""/>
        <v id="w_mss-dates_7658" ok="2" left="0" right="0" imgsig=""/>
        <v id="w_mss-dates_7659" ok="2" left="0" right="0" imgsig=""/>
        <v id="w_mss-dates_7660" ok="2" left="0" right="0" imgsig=""/>
        <v id="w_mss-dates_7661" ok="2" left="0" right="0" imgsig=""/>
        <v id="w_mss-dates_7662" ok="2" left="0" right="0" imgsig=""/>
        <v id="w_mss-dates_7663" ok="2" left="0" right="0" imgsig=""/>
        <v id="w_mss-dates_7664" ok="2" left="0" right="0" imgsig=""/>
        <v id="w_mss-dates_7665" ok="2" left="0" right="0" imgsig=""/>
        <v id="w_mss-dates_7666" ok="2" left="0" right="0" imgsig=""/>
        <v id="w_mss-dates_7667" ok="2" left="0" right="0" imgsig=""/>
        <v id="w_mss-dates_7668" ok="2" left="0" right="0" imgsig=""/>
        <v id="w_mss-dates_7669" ok="2" left="0" right="0" imgsig=""/>
        <v id="w_mss-dates_7670" ok="2" left="0" right="0" imgsig=""/>
        <v id="w_mss-dates_7671" ok="2" left="0" right="0" imgsig=""/>
        <v id="w_mss-dates_7672" ok="2" left="0" right="0" imgsig=""/>
        <v id="w_mss-dates_7673" ok="2" left="0" right="0" imgsig=""/>
        <v id="w_mss-dates_7674" ok="2" left="0" right="0" imgsig=""/>
        <v id="w_mss-dates_7675" ok="2" left="0" right="0" imgsig=""/>
        <v id="w_mss-dates_7676" ok="2" left="0" right="0" imgsig=""/>
        <v id="w_mss-dates_7677" ok="2" left="0" right="0" imgsig=""/>
        <v id="w_mss-dates_7678" ok="2" left="0" right="0" imgsig=""/>
        <v id="w_mss-dates_7679" ok="2" left="0" right="0" imgsig=""/>
        <v id="w_mss-dates_7680" ok="2" left="0" right="0" imgsig=""/>
        <v id="w_mss-dates_7681" ok="2" left="0" right="0" imgsig=""/>
        <v id="w_mss-dates_7682" ok="2" left="0" right="0" imgsig=""/>
        <v id="w_mss-dates_7683" ok="2" left="0" right="0" imgsig=""/>
        <v id="w_mss-dates_7684" ok="2" left="0" right="0" imgsig=""/>
        <v id="w_mss-dates_7685" ok="2" left="0" right="0" imgsig=""/>
        <v id="w_mss-dates_7686" ok="2" left="0" right="0" imgsig=""/>
        <v id="w_mss-dates_7687" ok="2" left="0" right="0" imgsig=""/>
        <v id="w_mss-dates_7688" ok="2" left="0" right="0" imgsig=""/>
        <v id="w_mss-dates_7689" ok="2" left="0" right="0" imgsig=""/>
        <v id="w_mss-dates_7690" ok="2" left="0" right="0" imgsig=""/>
        <v id="w_mss-dates_7691" ok="2" left="0" right="0" imgsig=""/>
        <v id="w_mss-dates_7694" ok="2" left="0" right="0" imgsig=""/>
        <v id="w_mss-dates_7695" ok="2" left="0" right="0" imgsig=""/>
        <v id="w_mss-dates_7696" ok="2" left="0" right="0" imgsig=""/>
        <v id="w_mss-dates_7697" ok="2" left="0" right="0" imgsig=""/>
        <v id="w_mss-dates_7700" ok="2" left="0" right="0" imgsig=""/>
        <v id="w_mss-dates_7701" ok="2" left="0" right="0" imgsig=""/>
        <v id="w_mss-dates_7702" ok="2" left="0" right="0" imgsig=""/>
        <v id="w_mss-dates_7703" ok="2" left="0" right="0" imgsig=""/>
        <v id="w_mss-dates_7704" ok="2" left="0" right="0" imgsig=""/>
        <v id="w_mss-dates_7705" ok="2" left="0" right="0" imgsig=""/>
        <v id="w_mss-dates_7706" ok="2" left="0" right="0" imgsig=""/>
        <v id="w_mss-dates_7707" ok="2" left="0" right="0" imgsig=""/>
        <v id="w_mss-dates_7708" ok="2" left="0" right="0" imgsig=""/>
        <v id="w_mss-dates_7709" ok="2" left="0" right="0" imgsig=""/>
        <v id="w_mss-dates_7710" ok="2" left="0" right="0" imgsig=""/>
        <v id="w_mss-dates_7711" ok="2" left="0" right="0" imgsig=""/>
        <v id="w_mss-dates_7712" ok="2" left="0" right="0" imgsig=""/>
        <v id="w_mss-dates_7713" ok="2" left="0" right="0" imgsig=""/>
    </validation>
    <medlines>
        <column id="col_IRHT_P_007378_1">
            <GraphicalLine lh="86">
                <LinearInterpolation>
                    <Point2DDouble x="137" y="75"/>
                    <Point2DDouble x="368" y="75"/>
                    <Point2DDouble x="575" y="75"/>
                    <Point2DDouble x="728" y="75"/>
                    <Point2DDouble x="938" y="75"/>
                    <Point2DDouble x="1161" y="75"/>
                    <Point2DDouble x="1391" y="75"/>
                    <Point2DDouble x="1448" y="75"/>
                    <Point2DDouble x="1627" y="75"/>
                    <Point2DDouble x="1729" y="75"/>
                </LinearInterpolation>
            </GraphicalLine>
            <GraphicalLine lh="79">
                <LinearInterpolation>
                    <Point2DDouble x="31" y="152"/>
                    <Point2DDouble x="149" y="152"/>
                    <Point2DDouble x="293" y="152"/>
                    <Point2DDouble x="374" y="152"/>
                    <Point2DDouble x="442" y="152"/>
                    <Point2DDouble x="530" y="152"/>
                    <Point2DDouble x="752" y="152"/>
                    <Point2DDouble x="1076" y="152"/>
                    <Point2DDouble x="1232" y="152"/>
                    <Point2DDouble x="1302" y="152"/>
                    <Point2DDouble x="1401" y="152"/>
                    <Point2DDouble x="1556" y="152"/>
                    <Point2DDouble x="1729" y="152"/>
                </LinearInterpolation>
            </GraphicalLine>
            <GraphicalLine lh="81">
                <LinearInterpolation>
                    <Point2DDouble x="37" y="226"/>
                    <Point2DDouble x="100" y="226"/>
                    <Point2DDouble x="235" y="226"/>
                    <Point2DDouble x="322" y="226"/>
                    <Point2DDouble x="586" y="226"/>
                    <Point2DDouble x="658" y="226"/>
                    <Point2DDouble x="808" y="226"/>
                    <Point2DDouble x="901" y="226"/>
                    <Point2DDouble x="1126" y="226"/>
                    <Point2DDouble x="1267" y="226"/>
                    <Point2DDouble x="1552" y="226"/>
                    <Point2DDouble x="1735" y="226"/>
                </LinearInterpolation>
            </GraphicalLine>
            <GraphicalLine lh="76">
                <LinearInterpolation>
                    <Point2DDouble x="36" y="296"/>
                    <Point2DDouble x="104" y="296"/>
                    <Point2DDouble x="292" y="296"/>
                    <Point2DDouble x="394" y="296"/>
                    <Point2DDouble x="534" y="296"/>
                    <Point2DDouble x="661" y="296"/>
                    <Point2DDouble x="917" y="296"/>
                    <Point2DDouble x="1122" y="296"/>
                    <Point2DDouble x="1280" y="296"/>
                    <Point2DDouble x="1485" y="296"/>
                    <Point2DDouble x="1595" y="296"/>
                    <Point2DDouble x="1732" y="296"/>
                </LinearInterpolation>
            </GraphicalLine>
            <GraphicalLine lh="87">
                <LinearInterpolation>
                    <Point2DDouble x="36" y="371"/>
                    <Point2DDouble x="272" y="371"/>
                    <Point2DDouble x="540" y="371"/>
                    <Point2DDouble x="672" y="371"/>
                    <Point2DDouble x="914" y="371"/>
                    <Point2DDouble x="1149" y="371"/>
                    <Point2DDouble x="1252" y="371"/>
                    <Point2DDouble x="1633" y="371"/>
                    <Point2DDouble x="1726" y="371"/>
                </LinearInterpolation>
            </GraphicalLine>
            <GraphicalLine lh="387">
                <LinearInterpolation>
                    <Point2DDouble x="36" y="467"/>
                    <Point2DDouble x="82" y="737"/>
                    <Point2DDouble x="255" y="467"/>
                    <Point2DDouble x="367" y="467"/>
                    <Point2DDouble x="725" y="467"/>
                    <Point2DDouble x="925" y="467"/>
                    <Point2DDouble x="985" y="467"/>
                    <Point2DDouble x="1078" y="467"/>
                    <Point2DDouble x="1390" y="467"/>
                    <Point2DDouble x="1473" y="467"/>
                    <Point2DDouble x="1641" y="467"/>
                    <Point2DDouble x="1687" y="467"/>
                    <Point2DDouble x="1729" y="467"/>
                </LinearInterpolation>
            </GraphicalLine>
            <GraphicalLine lh="109">
                <LinearInterpolation>
                    <Point2DDouble x="73" y="737"/>
                    <Point2DDouble x="236" y="737"/>
                    <Point2DDouble x="487" y="737"/>
                </LinearInterpolation>
            </GraphicalLine>
            <GraphicalLine lh="109">
                <LinearInterpolation>
                    <Point2DDouble x="478" y="737"/>
                    <Point2DDouble x="641" y="737"/>
                    <Point2DDouble x="770" y="737"/>
                    <Point2DDouble x="851" y="737"/>
                    <Point2DDouble x="957" y="737"/>
                    <Point2DDouble x="989" y="737"/>
                    <Point2DDouble x="1070" y="737"/>
                    <Point2DDouble x="1151" y="737"/>
                    <Point2DDouble x="1208" y="737"/>
                </LinearInterpolation>
            </GraphicalLine>
            <GraphicalLine lh="190">
                <LinearInterpolation>
                    <Point2DDouble x="44" y="879"/>
                    <Point2DDouble x="94" y="965"/>
                    <Point2DDouble x="160" y="879"/>
                    <Point2DDouble x="304" y="879"/>
                    <Point2DDouble x="440" y="879"/>
                    <Point2DDouble x="688" y="879"/>
                    <Point2DDouble x="853" y="879"/>
                    <Point2DDouble x="960" y="879"/>
                    <Point2DDouble x="1076" y="879"/>
                    <Point2DDouble x="1113" y="879"/>
                    <Point2DDouble x="1224" y="879"/>
                    <Point2DDouble x="1488" y="879"/>
                    <Point2DDouble x="1645" y="879"/>
                    <Point2DDouble x="1723" y="879"/>
                </LinearInterpolation>
            </GraphicalLine>
            <GraphicalLine lh="172">
                <LinearInterpolation>
                    <Point2DDouble x="86" y="965"/>
                    <Point2DDouble x="92" y="1044"/>
                    <Point2DDouble x="199" y="965"/>
                    <Point2DDouble x="472" y="965"/>
                    <Point2DDouble x="1048" y="965"/>
                    <Point2DDouble x="1308" y="965"/>
                    <Point2DDouble x="1408" y="965"/>
                    <Point2DDouble x="1667" y="965"/>
                </LinearInterpolation>
            </GraphicalLine>
            <GraphicalLine lh="89">
                <LinearInterpolation>
                    <Point2DDouble x="85" y="1044"/>
                    <Point2DDouble x="198" y="1044"/>
                    <Point2DDouble x="271" y="1044"/>
                    <Point2DDouble x="346" y="1044"/>
                    <Point2DDouble x="525" y="1044"/>
                    <Point2DDouble x="709" y="1044"/>
                    <Point2DDouble x="838" y="1044"/>
                    <Point2DDouble x="937" y="1044"/>
                    <Point2DDouble x="1158" y="1044"/>
                    <Point2DDouble x="1383" y="1044"/>
                    <Point2DDouble x="1515" y="1044"/>
                    <Point2DDouble x="1614" y="1044"/>
                    <Point2DDouble x="1736" y="1044"/>
                </LinearInterpolation>
            </GraphicalLine>
            <GraphicalLine lh="110">
                <LinearInterpolation>
                    <Point2DDouble x="39" y="1126"/>
                    <Point2DDouble x="236" y="1126"/>
                    <Point2DDouble x="269" y="1126"/>
                    <Point2DDouble x="498" y="1126"/>
                    <Point2DDouble x="641" y="1126"/>
                    <Point2DDouble x="792" y="1126"/>
                    <Point2DDouble x="1009" y="1126"/>
                    <Point2DDouble x="1086" y="1126"/>
                    <Point2DDouble x="1246" y="1126"/>
                    <Point2DDouble x="1376" y="1126"/>
                    <Point2DDouble x="1475" y="1126"/>
                    <Point2DDouble x="1585" y="1126"/>
                    <Point2DDouble x="1740" y="1126"/>
                </LinearInterpolation>
            </GraphicalLine>
        </column>
    </medlines>
    <lineLinks>
        <ll id="line_IRHT_P_007378_1-9" col="col_IRHT_P_007378_1" n="8"/>
        <ll id="line_IRHT_P_007378_1-1" col="col_IRHT_P_007378_1" n="0"/>
        <ll id="line_IRHT_P_007378_1-2" col="col_IRHT_P_007378_1" n="1"/>
        <ll id="line_IRHT_P_007378_1-3" col="col_IRHT_P_007378_1" n="2"/>
        <ll id="line_IRHT_P_007378_1-11" col="col_IRHT_P_007378_1" n="10"/>
        <ll id="line_IRHT_P_007378_1-4" col="col_IRHT_P_007378_1" n="3"/>
        <ll id="line_IRHT_P_007378_1-10" col="col_IRHT_P_007378_1" n="9"/>
        <ll id="line_IRHT_P_007378_1-5" col="col_IRHT_P_007378_1" n="4"/>
        <ll id="line_IRHT_P_007378_1-6" col="col_IRHT_P_007378_1" n="5"/>
        <ll id="line_IRHT_P_007378_1-12" col="col_IRHT_P_007378_1" n="11"/>
        <ll id="line_IRHT_P_007378_1-7" col="col_IRHT_P_007378_1" n="6"/>
        <ll id="line_IRHT_P_007378_1-8" col="col_IRHT_P_007378_1" n="7"/>
    </lineLinks>
</OriData>
